apolo_base_client/__init__.py
apolo_base_client/_client.py
apolo_base_client/py.typed
apolo_base_client-24.10.3.dist-info/LICENSE
apolo_base_client-24.10.3.dist-info/METADATA
apolo_base_client-24.10.3.dist-info/WHEEL
apolo_base_client-24.10.3.dist-info/RECORD
